README.md
setup.py
dreamapi/__init__.py
dreamapi/texttospeech/__init__.py
dreamapi/texttospeech/tts.py
dreamapi/utils/__init__.py
dreamapi/utils/synthesis.py
dreamapi/utils/upload.py
dreamapi/utils/utils.py
dreamapi/videogenerator/__init__.py
dreamapi/videogenerator/video_generator.py
dreamtest.egg-info/PKG-INFO
dreamtest.egg-info/SOURCES.txt
dreamtest.egg-info/dependency_links.txt
dreamtest.egg-info/not-zip-safe
dreamtest.egg-info/requires.txt
dreamtest.egg-info/top_level.txt